dlin/__init__.py
dlin/cube.py
dlin/piece.py
dlin/tracer.py
dlin-0.1.2.data/scripts/dlin-trace
dlin-0.1.2.dist-info/LICENSE
dlin-0.1.2.dist-info/METADATA
dlin-0.1.2.dist-info/WHEEL
dlin-0.1.2.dist-info/top_level.txt
dlin-0.1.2.dist-info/RECORD
