Metadata-Version: 2.1
Name: dlin
Version: 0.1.2
Summary: Describe the cycles on a scrambled Rubik's Cube
Home-page: https://github.com/elliottkobelansky/dlin
Author: Elliott Kobelansky
License: MIT
License-File: LICENSE
Requires-Dist: numpy
